{
    "gmail": {
        "email": "peakyblinder130307@gmail.com",
        "password": "%%3sG%53wk$w5Pyex"
    },
    "yahoo": {
        "email": "amilasuvan@yahoo.com",
        "password": "jmEEG6+5s%EI1h"
    },
    "openweather": {
        "email": "amilasuvan@yahoo.com",
        "password": "PD+C0IH$d7WIN"
    },
    "newsapi": {
        "email": "amilasuvan@gmail.com",
        "password": "zFk6)0UVw8gju&U6$!"
    },
    "nutritionix": {
        "email": "amilasuvan@yahoo.com",
        "password": "(d7$bFShdQK#6)3"
    },
    "kiwi": {
        "email": "amilasuvan@yahoo.com",
        "password": "L2E!5j#zJ7Vu4gu"
    }
}